airflow_docker_helper/__init__.py
airflow_docker_helper/__main__.py
airflow_docker_helper/compat.py
airflow_docker_helper/testing.py
airflow_docker_helper-0.2.0.dist-info/METADATA
airflow_docker_helper-0.2.0.dist-info/RECORD
airflow_docker_helper-0.2.0.dist-info/WHEEL
airflow_docker_helper-0.2.0.dist-info/entry_points.txt
airflow_docker_helper-0.2.0.dist-info/top_level.txt
