Metadata-Version: 2.1
Name: airflow-docker-helper
Version: 0.2.0
Summary: A light sdk to be used by the operators in airflow-docker and in task code to participate in host/container communication.
Home-page: https://github.com/huntcsg/airflow-docker-helper
Author: Hunter Senft-Grupp
Author-email: huntcsg@gmail.com
License: Apache License 2.0
Keywords: airflow docker
Platform: UNKNOWN
Classifier: Development Status :: 3 - Alpha
Classifier: Environment :: Console
Classifier: Environment :: Web Environment
Classifier: Intended Audience :: Developers
Classifier: Intended Audience :: System Administrators
Classifier: License :: OSI Approved :: Apache Software License
Classifier: Programming Language :: Python :: 2.7
Classifier: Programming Language :: Python :: 3.4
Classifier: Programming Language :: Python :: 3.5
Classifier: Programming Language :: Python :: 3.6
Classifier: Programming Language :: Python :: 3.7
Classifier: Topic :: System :: Monitoring
Requires-Python: >=2.7,!=3.0.*,!=3.1.*,!=3.2.*,!=3.3.*
Provides-Extra: docs
Provides-Extra: linting
Provides-Extra: testing
Provides-Extra: docs
Requires-Dist: sphinx; extra == 'docs'
Requires-Dist: sphinx-rtd-theme; extra == 'docs'
Provides-Extra: linting
Requires-Dist: isort; extra == 'linting'
Requires-Dist: black; extra == 'linting'
Requires-Dist: bumpversion; extra == 'linting'
Requires-Dist: flake8; extra == 'linting'
Provides-Extra: testing
Requires-Dist: pytest; extra == 'testing'
Requires-Dist: pytest-cov; extra == 'testing'
Provides-Extra: testing
Requires-Dist: mock; (python_version < "3") and extra == 'testing'
